noirnote_cli/__init__.py
noirnote_cli/api.py
noirnote_cli/auth.py
noirnote_cli/crypto.py
noirnote_cli/keychain.py
noirnote_cli/local_auth.py
noirnote_cli/main.py
noirnote_cli/sc.py
noirnote_cli-0.1.0.dist-info/METADATA
noirnote_cli-0.1.0.dist-info/WHEEL
noirnote_cli-0.1.0.dist-info/entry_points.txt
noirnote_cli-0.1.0.dist-info/top_level.txt
noirnote_cli-0.1.0.dist-info/RECORD
