Metadata-Version: 2.4
Name: noirnote-cli
Version: 0.1.0
Summary: A CLI for securely fetching secrets from the NoirNote application.
Home-page: https://github.com/sync0n/noirnote-cli
Author: NoirNote
Author-email: remikapler@gmail.com
License: MIT
Classifier: Development Status :: 4 - Beta
Classifier: Intended Audience :: Developers
Classifier: License :: OSI Approved :: MIT License
Classifier: Operating System :: OS Independent
Classifier: Programming Language :: Python :: 3
Classifier: Programming Language :: Python :: 3.8
Classifier: Programming Language :: Python :: 3.9
Classifier: Programming Language :: Python :: 3.10
Classifier: Programming Language :: Python :: 3.11
Classifier: Topic :: Security
Classifier: Topic :: Software Development :: Libraries :: Python Modules
Classifier: Topic :: Utilities
Requires-Python: >=3.8
Requires-Dist: click>=8.0
Requires-Dist: requests>=2.25
Requires-Dist: pycryptodome>=3.10
Requires-Dist: cryptography>=3.4
Requires-Dist: pyrebase4>=4.7.1
Requires-Dist: setuptools>=68.0
Requires-Dist: keyring>=24.0.0
Requires-Dist: keyrings.cryptfile>=1.3.4
Requires-Dist: questionary>=2.0.0
Requires-Dist: prompt_toolkit>=3.0.0
Requires-Dist: rich>=12.0.0
Dynamic: author
Dynamic: author-email
Dynamic: classifier
Dynamic: description
Dynamic: description-content-type
Dynamic: home-page
Dynamic: license
Dynamic: requires-dist
Dynamic: requires-python
Dynamic: summary
